logtrek/__init__.py
logtrek/logtrak.py
logtrek-0.2.4.dist-info/LICENSE.txt
logtrek-0.2.4.dist-info/METADATA
logtrek-0.2.4.dist-info/WHEEL
logtrek-0.2.4.dist-info/top_level.txt
logtrek-0.2.4.dist-info/RECORD
