Metadata-Version: 2.1
Name: logtrek
Version: 0.2.4
Summary: To generate a log tracking mechanism that can be customised.
Author: mose_tucker_0159
Author-email: mose.tucker.0159@gmail.com
Keywords: python
Classifier: Development Status :: 1 - Planning
Classifier: Intended Audience :: End Users/Desktop
Classifier: Programming Language :: Python :: 3
Classifier: Operating System :: Microsoft :: Windows
License-File: LICENSE.txt
Requires-Dist: bips
